client_app/__init__.py
client_app/client.py
client_app/common/__init__.py
client_app/common/exceptions.py
client_app/common/transport.py
client_app/common/utils.py
client_app/common/variables.py
client_app/common/verifiers.py
client_app/db/__init__.py
client_app/db/client_storage.py
client_app/db/db_connect.py
client_app/db/db_messages.py
client_app/logs/__init__.py
client_app/logs/client_log_config.py
client_app/logs/decorators.py
client_app/views/__init__.py
client_app/views/add_contact.py
client_app/views/client_gui.py
client_app/views/nickname.py
monster_chat_client-1.0.0.dist-info/METADATA
monster_chat_client-1.0.0.dist-info/WHEEL
monster_chat_client-1.0.0.dist-info/top_level.txt
monster_chat_client-1.0.0.dist-info/RECORD
