Metadata-Version: 2.1
Name: monster-chat-client
Version: 1.0.0
Summary: MMMMonsterChat client application
Home-page: UNKNOWN
Author: KTo ETo
Author-email: kto@lovetou.ru
License: UNKNOWN
Platform: UNKNOWN
Requires-Dist: PyQt5
Requires-Dist: sqlalchemy
Requires-Dist: pycryptodome
Requires-Dist: pycryptodomex
